SR/Lab02/delayer/delayer.v
`timescale 1ns / 1ps
//////////////////////////////////////////////////////////////////////////////////
// Company: 
// Engineer: 
// 
// Create Date: 03/06/2023 02:01:15 PM
// Design Name: 
// Module Name: delayer
// Project Name: 
// Target Devices: 
// Tool Versions: 
// Description: 
// 
// Dependencies: 
// 
// Revision:
// Revision 0.01 - File Created
// Additional Comments:
// 
//////////////////////////////////////////////////////////////////////////////////


module delayer#(
    parameter N = 8,
    parameter DELAY = 4
)(
    input clk,
    input [N-1:0] i_data,
    output [N-1:0] o_data,
    input ce
    );

integer i;

generate

if(DELAY == 0) begin
    assign o_data = i_data;
end else begin
    reg [N-1:0] temp [DELAY:0];
    assign o_data = temp[DELAY];
    always @(posedge clk) begin
       temp[0] <= i_data;
       for(i = 1; i<DELAY; i = i+1) begin
            temp[i] <= temp[i-1];
       end
    end
end

endgenerate

endmodule

SR/Lab02/delayer/delayer_tb.v
`timescale 1ns / 1ps
//////////////////////////////////////////////////////////////////////////////////
// Company: 
// Engineer: 
// 
// Create Date: 03/06/2023 02:40:55 PM
// Design Name: 
// Module Name: delayer_tb
// Project Name: 
// Target Devices: 
// Tool Versions: 
// Description: 
// 
// Dependencies: 
// 
// Revision:
// Revision 0.01 - File Created
// Additional Comments:
// 
//////////////////////////////////////////////////////////////////////////////////

`include "delayer.v"

module delayer_tb();
    
localparam DELAY = 4;
localparam N = 8;

delayer #(.DELAY(DELAY), .N(N)) uut (.i_data(i_data), .o_data(o_data), .clk(clk), .ce(ce));

reg clk = 1'b0;
reg [N-1:0] i_data = 8'h55;
wire [N-1:0] o_data;
reg ce = 1'b1;

initial begin
    $dumpfile("delayer_tb.vcd");
    $dumpvars;
    #100 $finish;
end

always 
begin
    #1; clk <= ~clk;    
end

endmodule

SR/Lab02/delayer/.build/delayer_tb.vcd
$date
	Mon Mar 06 15:06:46 2023
$end
$version
	Icarus Verilog
$end
$timescale
	1ps
$end
$scope module delayer_tb $end
$var wire 8 ! o_data [7:0] $end
$var reg 1 " ce $end
$var reg 1 # clk $end
$var reg 8 $ i_data [7:0] $end
$scope module uut $end
$var wire 1 " ce $end
$var wire 1 # clk $end
$var wire 8 % i_data [7:0] $end
$var wire 8 & o_data [7:0] $end
$var integer 32 ' i [31:0] $end
$scope begin genblk1 $end
$upscope $end
$upscope $end
$upscope $end
$enddefinitions $end
#0
$dumpvars
bx '
bx &
b1010101 %
b1010101 $
0#
1"
bx !
$end
#1000
b100 '
1#
#2000
0#
#3000
b100 '
1#
#4000
0#
#5000
b100 '
1#
#6000
0#
#7000
b100 '
1#
#8000
0#
#9000
b100 '
1#
#10000
0#
#11000
b100 '
1#
#12000
0#
#13000
b100 '
1#
#14000
0#
#15000
b100 '
1#
#16000
0#
#17000
b100 '
1#
#18000
0#
#19000
b100 '
1#
#20000
0#
#21000
b100 '
1#
#22000
0#
#23000
b100 '
1#
#24000
0#
#25000
b100 '
1#
#26000
0#
#27000
b100 '
1#
#28000
0#
#29000
b100 '
1#
#30000
0#
#31000
b100 '
1#
#32000
0#
#33000
b100 '
1#
#34000
0#
#35000
b100 '
1#
#36000
0#
#37000
b100 '
1#
#38000
0#
#39000
b100 '
1#
#40000
0#
#41000
b100 '
1#
#42000
0#
#43000
b100 '
1#
#44000
0#
#45000
b100 '
1#
#46000
0#
#47000
b100 '
1#
#48000
0#
#49000
b100 '
1#
#50000
0#
#51000
b100 '
1#
#52000
0#
#53000
b100 '
1#
#54000
0#
#55000
b100 '
1#
#56000
0#
#57000
b100 '
1#
#58000
0#
#59000
b100 '
1#
#60000
0#
#61000
b100 '
1#
#62000
0#
#63000
b100 '
1#
#64000
0#
#65000
b100 '
1#
#66000
0#
#67000
b100 '
1#
#68000
0#
#69000
b100 '
1#
#70000
0#
#71000
b100 '
1#
#72000
0#
#73000
b100 '
1#
#74000
0#
#75000
b100 '
1#
#76000
0#
#77000
b100 '
1#
#78000
0#
#79000
b100 '
1#
#80000
0#
#81000
b100 '
1#
#82000
0#
#83000
b100 '
1#
#84000
0#
#85000
b100 '
1#
#86000
0#
#87000
b100 '
1#
#88000
0#
#89000
b100 '
1#
#90000
0#
#91000
b100 '
1#
#92000
0#
#93000
b100 '
1#
#94000
0#
#95000
b100 '
1#
#96000
0#
#97000
b100 '
1#
#98000
0#
#99000
b100 '
1#
